conf2env/__init__.py
conf2env/__main__.py
conf2env/convert.py
conf2env/importer.py
conf2env-0.0.1b2.dist-info/LICENSE
conf2env-0.0.1b2.dist-info/WHEEL
conf2env-0.0.1b2.dist-info/METADATA
conf2env-0.0.1b2.dist-info/RECORD
